cozytouchpy/__init__.py
cozytouchpy/client.py
cozytouchpy/constant.py
cozytouchpy/exception.py
cozytouchpy/handlers.py
cozytouchpy/utils.py
cozytouchpy/objects/__init__.py
cozytouchpy/objects/boiler.py
cozytouchpy/objects/climate.py
cozytouchpy/objects/device.py
cozytouchpy/objects/gateway.py
cozytouchpy/objects/heater.py
cozytouchpy/objects/heatpump.py
cozytouchpy/objects/object.py
cozytouchpy/objects/place.py
cozytouchpy/objects/pod.py
cozytouchpy/objects/sensors.py
cozytouchpy/objects/waterheater.py
cozytouchpy-3.6.dist-info/LICENSE
cozytouchpy-3.6.dist-info/METADATA
cozytouchpy-3.6.dist-info/WHEEL
cozytouchpy-3.6.dist-info/top_level.txt
cozytouchpy-3.6.dist-info/RECORD
